termikanban/__init__.py
termikanban/kanban_board.py
termikanban/main.py
termikanban-1.0.1.dist-info/licenses/LICENSE.txt
termikanban-1.0.1.dist-info/METADATA
termikanban-1.0.1.dist-info/WHEEL
termikanban-1.0.1.dist-info/entry_points.txt
termikanban-1.0.1.dist-info/top_level.txt
termikanban-1.0.1.dist-info/RECORD
