Metadata-Version: 2.4
Name: termikanban
Version: 1.0.1
Summary: A terminal-based Kanban board application.
Author-email: ArmadilloMike <armadillomike@armadillomike.dev>
License: MIT
Project-URL: Homepage, https://github.com/armadillomike/termikanban
Requires-Python: >=3.6
License-File: LICENSE.txt
Dynamic: license-file
